JupyterNotebook60ZhongwenWendang/README.md
JupyterNotebook60ZhongwenWendang/__init__.py
JupyterNotebook60ZhongwenWendang/__main__.py
JupyterNotebook60ZhongwenWendang/file.epub
JupyterNotebook60ZhongwenWendang/index.html
JupyterNotebook60ZhongwenWendang/css/__init__.py
JupyterNotebook60ZhongwenWendang/css/annotations.css
JupyterNotebook60ZhongwenWendang/css/main.css
JupyterNotebook60ZhongwenWendang/css/normalize.css
JupyterNotebook60ZhongwenWendang/css/popup.css
JupyterNotebook60ZhongwenWendang/font/__init__.py
JupyterNotebook60ZhongwenWendang/font/fontello.eot
JupyterNotebook60ZhongwenWendang/font/fontello.svg
JupyterNotebook60ZhongwenWendang/font/fontello.ttf
JupyterNotebook60ZhongwenWendang/font/fontello.woff
JupyterNotebook60ZhongwenWendang/img/__init__.py
JupyterNotebook60ZhongwenWendang/img/annotator-glyph-sprite.png
JupyterNotebook60ZhongwenWendang/img/annotator-icon-sprite.png
JupyterNotebook60ZhongwenWendang/img/apple-touch-icon.png
JupyterNotebook60ZhongwenWendang/img/cancelfullscreen.png
JupyterNotebook60ZhongwenWendang/img/close.png
JupyterNotebook60ZhongwenWendang/img/fullscreen.png
JupyterNotebook60ZhongwenWendang/img/loader.gif
JupyterNotebook60ZhongwenWendang/img/menu-icon.png
JupyterNotebook60ZhongwenWendang/img/save.png
JupyterNotebook60ZhongwenWendang/img/saved.png
JupyterNotebook60ZhongwenWendang/img/settings-s.png
JupyterNotebook60ZhongwenWendang/img/settings.png
JupyterNotebook60ZhongwenWendang/img/star.png
JupyterNotebook60ZhongwenWendang/js/__init__.py
JupyterNotebook60ZhongwenWendang/js/epub.js
JupyterNotebook60ZhongwenWendang/js/epub.min.js
JupyterNotebook60ZhongwenWendang/js/epub.min.map
JupyterNotebook60ZhongwenWendang/js/hooks.min.js
JupyterNotebook60ZhongwenWendang/js/hooks.min.map
JupyterNotebook60ZhongwenWendang/js/reader.js
JupyterNotebook60ZhongwenWendang/js/reader.js.map
JupyterNotebook60ZhongwenWendang/js/reader.min.js
JupyterNotebook60ZhongwenWendang/js/reader.min.map
JupyterNotebook60ZhongwenWendang/js/hooks/__init__.py
jupyter_notebook_6_0_zhongwen_wendang-2024.3.5.0.dist-info/METADATA
jupyter_notebook_6_0_zhongwen_wendang-2024.3.5.0.dist-info/WHEEL
jupyter_notebook_6_0_zhongwen_wendang-2024.3.5.0.dist-info/entry_points.txt
jupyter_notebook_6_0_zhongwen_wendang-2024.3.5.0.dist-info/top_level.txt
jupyter_notebook_6_0_zhongwen_wendang-2024.3.5.0.dist-info/RECORD
